{
    "backend": "django",
    "db_name": "",
    "db_pass": "",
    "db_type": "sqlite",
    "db_user": "",
    "dbms": "1",
    "description": "generated product",
    "design": "datta-able",
    "docker": "0",
    "err_code": 0,
    "frontend": "",
    "heroku": "0",
    "pattern": "mvc",
    "pro": "0",
    "task_id": "4b1b5082-8723-401c-a9e0-b8022b29f6ab",
    "task_info": "Upload Sources [0%] - 163 files",
    "task_output": "4b1b5082-8723-401c-a9e0-b8022b29f6ab.zip",
    "task_result": "SUCCESS",
    "task_state": "RUNNING",
    "task_ts_end": "2024-11-21-23-31-04",
    "task_ts_start": "2024-11-21-23-31-01"
}